behavior_planner/README.md
behavior_planner/__init__.py
behavior_planner/behavior_module.py
behavior_planner/utils/FSM_logic_modules.py
behavior_planner/utils/FSM_model.py
behavior_planner/utils/__init__.py
behavior_planner/utils/helper_functions.py
behavior_planner/utils/path_planner.py
behavior_planner/utils/velocity_planner.py
cr_scenario_handler/README.md
cr_scenario_handler/__init__.py
cr_scenario_handler/doxygen/Doxyfile
cr_scenario_handler/evaluation/agent_evaluation.py
cr_scenario_handler/evaluation/collision_report.py
cr_scenario_handler/evaluation/metrics.py
cr_scenario_handler/evaluation/simulation_evaluation.py
cr_scenario_handler/planner_interfaces/__init__.py
cr_scenario_handler/planner_interfaces/frenet_interface.py
cr_scenario_handler/planner_interfaces/planner_interface.py
cr_scenario_handler/simulation/__init__.py
cr_scenario_handler/simulation/agent.py
cr_scenario_handler/simulation/agent_batch.py
cr_scenario_handler/simulation/simulation.py
cr_scenario_handler/utils/__init__.py
cr_scenario_handler/utils/agent_status.py
cr_scenario_handler/utils/collision_check.py
cr_scenario_handler/utils/configuration.py
cr_scenario_handler/utils/configuration_builder.py
cr_scenario_handler/utils/evaluation.py
cr_scenario_handler/utils/general.py
cr_scenario_handler/utils/goalcheck.py
cr_scenario_handler/utils/helper_functions.py
cr_scenario_handler/utils/multiagent_helpers.py
cr_scenario_handler/utils/multiagent_logging.py
cr_scenario_handler/utils/prediction_helpers.py
cr_scenario_handler/utils/sensor_model.py
cr_scenario_handler/utils/utils_coordinate_system.py
cr_scenario_handler/utils/velocity_planner.py
cr_scenario_handler/utils/visualization.py
frenetix_motion_planner/__init__.py
frenetix_motion_planner/cost_functions/__init__.py
frenetix_motion_planner/cost_functions/cost_function.py
frenetix_motion_planner/cost_functions/partial_cost_functions.py
frenetix_motion_planner/planner.py
frenetix_motion_planner/polynomial_trajectory.py
frenetix_motion_planner-2024.1.1.dist-info/LICENSE
frenetix_motion_planner-2024.1.1.dist-info/METADATA
frenetix_motion_planner-2024.1.1.dist-info/WHEEL
frenetix_motion_planner-2024.1.1.dist-info/entry_points.txt
frenetix_motion_planner-2024.1.1.dist-info/RECORD
