Metadata-Version: 2.1
Name: frenetix-motion-planner
Version: 2024.1.1
Summary: Frenetix Motion Planner: Sampling-based Frenet Planner & Multi-agent CommonRoad Scenario Handler
License: LGPL-3.0-or-later
Author: Rainer Trauth
Author-email: rainer.trauth@tum.de
Maintainer: Rainer Trauth
Maintainer-email: rainer.trauth@tum.de
Requires-Python: >=3.9,<3.11
Classifier: License :: OSI Approved :: GNU Lesser General Public License v3 or later (LGPLv3+)
Classifier: Programming Language :: Python :: 3
Classifier: Programming Language :: Python :: 3.9
Classifier: Programming Language :: Python :: 3.10
Requires-Dist: commonroad-drivability-checker (>=2023.1,<2024.0)
Requires-Dist: commonroad-io (==2023.2)
Requires-Dist: commonroad-route-planner (>=2022.3,<2023.0)
Requires-Dist: commonroad-vehicle-models (>=3.0.2,<4.0.0)
Requires-Dist: frenetix (==0.1.3)
Requires-Dist: frenetix-occlusion (>=2024.1.2)
Requires-Dist: imageio (>=2.31.2,<3.0.0)
Requires-Dist: matplotlib (>=3.8.1,<4.0.0)
Requires-Dist: methodtools (>=0.4.7,<0.5.0)
Requires-Dist: numpy (>=1.24.2,<2.0.0)
Requires-Dist: omegaconf (>=2.1.1,<3.0.0)
Requires-Dist: onnxruntime (>=1.16.3,<2.0.0)
Requires-Dist: pandas (>=2.0.3,<3.0.0)
Requires-Dist: psutil (>=5.9.6)
Requires-Dist: pygeos (>=0.14,<0.15)
Requires-Dist: scipy (>=1.9.3,<2.0.0)
Requires-Dist: shapely (>=2.0.2,<3.0.0)
Requires-Dist: triangle (>=20200424)
Requires-Dist: wale-net (>=3.0.3)
Requires-Dist: wheel (>=0.38.4,<0.39.0)
